README.txt
setup.py
collective/__init__.py
collective.ptg.flickr.egg-info/PKG-INFO
collective.ptg.flickr.egg-info/SOURCES.txt
collective.ptg.flickr.egg-info/dependency_links.txt
collective.ptg.flickr.egg-info/entry_points.txt
collective.ptg.flickr.egg-info/namespace_packages.txt
collective.ptg.flickr.egg-info/not-zip-safe
collective.ptg.flickr.egg-info/requires.txt
collective.ptg.flickr.egg-info/top_level.txt
collective/ptg/__init__.py
collective/ptg/flickr/__init__.py
collective/ptg/flickr/configure.zcml
collective/ptg/flickr/tests/test_various.py
docs/HISTORY.txt
docs/INSTALL.txt