Metadata-Version: 1.0
Name: collective.ptg.flickr
Version: 0.1
Summary: Add on collective.plonetruegallery to aggregate from flickr
Home-page: http://www.plone.org/products/plone-true-gallery
Author: Nathan Van Gheem
Author-email: vangheem@gmail.com
License: GPL
Keywords: gallery flickr
Platform: UNKNOWN
Classifier: Framework :: Plone
Classifier: Programming Language :: Python
Classifier: Topic :: Software Development :: Libraries :: Python Modules
Classifier: Framework :: Plone :: 3.3
Classifier: Framework :: Plone :: 4.0
Classifier: Framework :: Plone :: 4.1
Classifier: Framework :: Plone :: 4.2
